bioencoder/__init__.py
bioencoder/config.py
bioencoder/core/__init__.py
bioencoder/core/augmentations.py
bioencoder/core/backbones.py
bioencoder/core/datasets.py
bioencoder/core/losses.py
bioencoder/core/models.py
bioencoder/core/optimizers.py
bioencoder/core/schedulers.py
bioencoder/core/utils.py
bioencoder/scripts/__init__.py
bioencoder/scripts/archive.py
bioencoder/scripts/configure.py
bioencoder/scripts/inference.py
bioencoder/scripts/interactive_plots.py
bioencoder/scripts/lr_finder.py
bioencoder/scripts/model_explorer.py
bioencoder/scripts/model_explorer_wrapper.py
bioencoder/scripts/split_dataset.py
bioencoder/scripts/swa.py
bioencoder/scripts/train.py
bioencoder/vis/__init__.py
bioencoder/vis/classes.py
bioencoder/vis/helpers.py
bioencoder/vis/methods.py
bioencoder/vis/methods_backup.py
bioencoder-1.0.1.dist-info/licenses/LICENSE
bioencoder-1.0.1.dist-info/METADATA
bioencoder-1.0.1.dist-info/WHEEL
bioencoder-1.0.1.dist-info/entry_points.txt
bioencoder-1.0.1.dist-info/top_level.txt
bioencoder-1.0.1.dist-info/RECORD
