Metadata-Version: 2.4
Name: bioencoder
Version: 1.0.1
Summary: A metric learning toolkit
Author-email: Arthur Porto <agporto@gmail.com>, Moritz Lürig <moritz.luerig@gmail.com>
Project-URL: Homepage, https://github.com/agporto/BioEncoder
Project-URL: Bug Tracker, https://github.com/agporto/BioEncoder/issues
Keywords: metric learning,biology
Requires-Python: >=3.9
License-File: LICENSE
Requires-Dist: albumentations==1.3.0
Requires-Dist: bokeh
Requires-Dist: faiss-cpu
Requires-Dist: ipywidgets
Requires-Dist: matplotlib
Requires-Dist: numpy
Requires-Dist: pandas
Requires-Dist: pytorch-metric-learning==2.0.1
Requires-Dist: scikit-learn
Requires-Dist: streamlit-option-menu
Requires-Dist: tensorboard
Requires-Dist: timm
Requires-Dist: torch-ema==0.3.0
Requires-Dist: torch-lr-finder
Requires-Dist: torch-optimizer==0.3.0
Dynamic: license-file
